{
	"name": "week_5_Avro1",
	"properties": {
		"linkedServiceName": {
			"referenceName": "AzureBlobStorage1",
			"type": "LinkedServiceReference"
		},
		"parameters": {
			"TableName": {
				"type": "string"
			}
		},
		"annotations": [],
		"type": "Avro",
		"typeProperties": {
			"location": {
				"type": "AzureBlobStorageLocation",
				"fileName": {
					"value": "@dataset().TableName",
					"type": "Expression"
				},
				"folderPath": "avro",
				"container": "week-5"
			}
		},
		"schema": {}
	}
}